LICENSE
MANIFEST.in
README.md
setup.py
syned_gui/__init__.py
syned_gui/version.py
syned_gui.egg-info/PKG-INFO
syned_gui.egg-info/SOURCES.txt
syned_gui.egg-info/dependency_links.txt
syned_gui.egg-info/namespace_packages.txt
syned_gui.egg-info/not-zip-safe
syned_gui.egg-info/requires.txt
syned_gui.egg-info/top_level.txt
syned_gui/beamline_rendering/__init__.py
syned_gui/beamline_rendering/ow_abstract_beamline_renderer.py
syned_gui/error_profile/__init__.py
syned_gui/error_profile/abstract_dabam_height_profile.py
syned_gui/error_profile/abstract_height_profile_simulator.py
syned_gui/error_profile/abstract_multiple_height_profile_simulator_S.py
syned_gui/error_profile/abstract_multiple_height_profile_simulator_T.py